streamget/__init__.py
streamget/__version__.py
streamget/cli.py
streamget/data.py
streamget/help.py
streamget/js/crypto-js.min.js
streamget/js/haixiu.js
streamget/js/laixiu.js
streamget/js/liveme.js
streamget/js/migu.js
streamget/js/taobao-sign.js
streamget/js/x-bogus.js
streamget/platforms/__init__.py
streamget/platforms/acfun/__init__.py
streamget/platforms/acfun/live_stream.py
streamget/platforms/baidu/__init__.py
streamget/platforms/baidu/live_stream.py
streamget/platforms/base.py
streamget/platforms/bigo/__init__.py
streamget/platforms/bigo/live_stream.py
streamget/platforms/bilibili/__init__.py
streamget/platforms/bilibili/live_stream.py
streamget/platforms/blued/__init__.py
streamget/platforms/blued/live_stream.py
streamget/platforms/changliao/__init__.py
streamget/platforms/changliao/live_stream.py
streamget/platforms/chzzk/__init__.py
streamget/platforms/chzzk/live_stream.py
streamget/platforms/douyin/__init__.py
streamget/platforms/douyin/live_stream.py
streamget/platforms/douyin/utils.py
streamget/platforms/douyu/__init__.py
streamget/platforms/douyu/live_stream.py
streamget/platforms/faceit/__init__.py
streamget/platforms/faceit/live_stream.py
streamget/platforms/flextv/__init__.py
streamget/platforms/flextv/live_stream.py
streamget/platforms/haixiu/__init__.py
streamget/platforms/haixiu/live_stream.py
streamget/platforms/huajiao/__init__.py
streamget/platforms/huajiao/live_stream.py
streamget/platforms/huamao/__init__.py
streamget/platforms/huamao/live_stream.py
streamget/platforms/huya/__init__.py
streamget/platforms/huya/live_stream.py
streamget/platforms/inke/__init__.py
streamget/platforms/inke/live_stream.py
streamget/platforms/jd/__init__.py
streamget/platforms/jd/live_stream.py
streamget/platforms/kuaishou/__init__.py
streamget/platforms/kuaishou/live_stream.py
streamget/platforms/kugou/__init__.py
streamget/platforms/kugou/live_stream.py
streamget/platforms/laixiu/__init__.py
streamget/platforms/laixiu/live_stream.py
streamget-4.0.8.dist-info/entry_points.txt
streamget-4.0.8.dist-info/LICENSE
streamget-4.0.8.dist-info/METADATA
streamget-4.0.8.dist-info/WHEEL
streamget-4.0.8.dist-info/RECORD
