Metadata-Version: 2.3
Name: streamget
Version: 4.0.8
Summary: A Multi-Platform Live Stream Parser Library.
License: MIT
Keywords: live,stream
Author: Hmily
Requires-Python: >=3.10,<4.0
Classifier: License :: OSI Approved :: MIT License
Classifier: Programming Language :: Python :: 3
Classifier: Programming Language :: Python :: 3.10
Classifier: Programming Language :: Python :: 3.11
Classifier: Programming Language :: Python :: 3.12
Classifier: Programming Language :: Python :: 3.13
Requires-Dist: PyExecJS (>=1.5.1)
Requires-Dist: distro (>=1.9.0)
Requires-Dist: httpx[http2] (>=0.28.1)
Requires-Dist: loguru (>=0.7.3)
Requires-Dist: pycryptodome (>=3.20.0)
Requires-Dist: requests (>=2.31.0)
Requires-Dist: tqdm (>=4.67.1)
Project-URL: Changelog, https://github.com/ihmily/streamget/blob/main/CHANGELOG.md
Project-URL: Documentation, https://streamget.readthedocs.io
Project-URL: Homepage, https://github.com/ihmily/streamget
Project-URL: Source, https://github.com/ihmily/streamget
